README.rst
setup.py
gogeta_configure/__init__.py
gogeta_configure/main.py
gogeta_configure.egg-info/PKG-INFO
gogeta_configure.egg-info/SOURCES.txt
gogeta_configure.egg-info/dependency_links.txt
gogeta_configure.egg-info/entry_points.txt
gogeta_configure.egg-info/requires.txt
gogeta_configure.egg-info/top_level.txt