Metadata-Version: 1.0
Name: gogeta-configure
Version: 0.0.3
Summary: gogeta-configure: Maintain etcd configuration for gogeta from YAML file
Home-page: https://github.com/samjsharpe/gogeta-configure
Author: Sam J Sharpe
Author-email: sam@samsharpe.net
License: MIT
Keywords: gogeta etcd yaml
Platform: UNKNOWN
